dingdb/__init__.py
dingdb/migrations/1-create-dingdb-schema.py
dingdb-0.0.2.data/data/dingdb/migrations/1-create-dingdb-schema.py
dingdb-0.0.2.dist-info/METADATA
dingdb-0.0.2.dist-info/WHEEL
dingdb-0.0.2.dist-info/entry_points.txt
dingdb-0.0.2.dist-info/top_level.txt
dingdb-0.0.2.dist-info/RECORD
