Metadata-Version: 2.1
Name: dingdb
Version: 0.0.2
Summary: UNKNOWN
Home-page: UNKNOWN
Author: Chris Simpson
Author-email: chris@karmacomputing.co.uk
License: UNKNOWN
Platform: UNKNOWN
Classifier: Programming Language :: Python :: 3
Classifier: License :: OSI Approved :: GNU Affero General Public License v3
Classifier: Operating System :: OS Independent
